[{"id":64,"name":"Leann","age":133},{"id":3,"name":"Clementine Bauch","age":13},{"id":10,"name":"Clementina DuBuque","age":20},{"id":12,"name":"Leanne ","age":21},{"id":11,"name":"Leanne ","age":22},{"id":13,"name":"Leanne ","age":23},{"id":13,"name":"Leanne ","age":15},{"id":3,"name":"Leanne ","age":15},{"id":3,"name":"Leanne ","age":15},{"id":3,"name":"Leanne ","age":15},{"id":3,"name":"Leanne ","age":149},{"id":3,"name":"Leanne ","age":0},{"id":3,"name":"Leanne ","age":0},{"id":3,"name":"Leanne ","age":25},{"id":3,"name":"Leanne ","age":34},{"id":5,"name":"Leanne","age":28},{"id":5,"name":"Leanne","age":35},{"id":5,"name":"Leannefsdfsdfffffffffffffffffffffffffffffffffffffffffffffsssssssssssssssssssssssssaaaaaaaaa","age":35},{"id":5,"name":"Leannefsdfsdfffffffffffffffffffffffffffffffffffffffffffffsssssssssssssssssssssssssaaaaaaaaa","age":35},{"id":5,"name":"Leanne","age":4},{"id":5,"name":"Leann","age":19},{"id":68,"name":"Leann","age":133}]